biobot/__init__.py
biobot/_modidx.py
biobot/_nbdev.py
biobot/base.py
biobot/completion.py
biobot/constants.py
biobot/discord.py
biobot/moderation.py
biobot/utils.py
biobot/whatsapp.py
biobot/yowsup.py
biobot-0.0.2.dist-info/LICENSE
biobot-0.0.2.dist-info/METADATA
biobot-0.0.2.dist-info/WHEEL
biobot-0.0.2.dist-info/top_level.txt
biobot-0.0.2.dist-info/RECORD
